[
    {
        "id": 1,
        "title": "Vehicle QR Sticker",
        "subtitle": "Smart identification",
        "price": 499,
        "oldPrice": 799,
        "discount": "37% OFF",
        "imgOne": "/images/product.svg",
        "imgTwo": "/images/product.svg",
        "categories": [
            "Vehicle QR"
        ],
        "size": [
            "Standard"
        ],
        "availability": "In Stock",
        "colors": [
            "bg-black",
            "bg-white"
        ],
        "review": 4.8,
        "shortDesc": "Easily link your vehicle details, emergency contacts, and parking info to a scanned QR code."
    },
    {
        "id": 2,
        "title": "Pet QR Tag",
        "subtitle": "Smart collar tag",
        "price": 299,
        "oldPrice": 499,
        "discount": "40% OFF",
        "imgOne": "/images/product.svg",
        "imgTwo": "/images/product.svg",
        "categories": [
            "Pet"
        ],
        "size": [
            "Small",
            "Large"
        ],
        "availability": "In Stock",
        "colors": [
            "bg-blue-500",
            "bg-red-500"
        ],
        "review": 4.9,
        "shortDesc": "Never lose your furry friends. Anyone scanning the tag can contact you instantly."
    },
    {
        "id": 3,
        "title": "Miscellaneous QR Code",
        "subtitle": "   ",
        "price": 199,
        "oldPrice": 299,
        "discount": "33% OFF",
        "imgOne": "/images/product.svg",
        "imgTwo": "/images/product.svg",
        "categories": [
            "Miscellaneous QR"
        ],
        "size": [
            "Standard"
        ],
        "availability": "In Stock",
        "colors": [
            "bg-gray-500"
        ],
        "review": 4.5,
        "shortDesc": "A versatile QR code for luggage, keys, or any personal items to help them get returned when lost."
    }
]